{
  "navigation": {
    "home": "בית",
    "pricing": "תמחור",
    "reports": "הדוחות שלי",
    "about": "אודותינו",
    "contact": "צור קשר",
    "login": "היכנס",
    "logout": "התנתק",
    "upgrade": "שדרג ל-Pro"
  },
  "languageSwitcher": {
    "english": "אנגלית",
    "hebrew": "עברית"
  },
  "hero": {
    "title": "ברוכים הבאים ל-Paynalyze.<br />ניתוח שכר פשוט",
    "subtitle": "העלה, נתח ובדוק בקלות את דוחות השכר שלך.",
    "uploadTitle": "העלה את תלוש השכר וחוזה העסקה שלך",
    "uploadSubtitle": "הגש את המסמכים שלך לניתוח שכר מומחה. אין צורך להזין פרטים אישיים!",
    "payslipUploadTitle": "העלאת תלוש שכר",
    "payslipUploadText": "גרור את הקובץ לכאן, או דפדף (PDF, TIF, PNG, JPG)",
    "contractUploadTitle": "העלאת חוזה העסקה",
    "contractUploadText": "גרור את הקובץ לכאן, או דפדף (PDF, TIF, PNG, JPG)",
    "attendanceUploadTitle": "העלאת דוחות נוכחות",
    "attendanceUploadText": "גרור את הקובץ לכאן, או דפדף (PDF, TIF, PNG, JPG)",
    "uploadButton": "העלה קובץ",
    "actionButtons": {
      "createReport": "צור דוח",
      "createCompanyPage": "צור דף חברה",
      "documentHistory": "היסטוריית מסמכים",
      "prepareClaim": "הכנת תביעה",
      "checkProfitability": "בדוק רווחיות",
      "createWarningLetter": "צור מכתב אזהרה",
      "professionalOpinion": "חוות דעת מקצועית וחישובים",
      "predictSuccess": "חיזוי הצלחה",
      "finalClaimReport": "דוח תביעה סופי וטבלאות",
      "identifySerialEmployer": "זיהוי מעסיק סדרתי",
      "easyExplanation": "הסבר פשוט"
    },
    "sharing": {
      "title": "שלח דוחות באמצעות:",
      "whatsapp": "שלח באמצעות וואטסאפ",
      "email": "שלח באמצעות אימייל",
      "findLawyer": "מצא את עורך הדין שלך"
    }
  },
  "howItWorks": {
    "title": "איך <span class=\"text-yellow\">Paynalyze</span> עובד.",
    "subtitle": "ציות קל לשכר ב-3 שלבים",
    "steps": [
      {
        "title": "העלה את תלוש השכר שלך",
        "description": "סרוק והגש את מסמך השכר שלך."
      },
      {
        "title": "ניתוח משפטי AI",
        "description": "זהה הפרות באופן מיידי ובדוק תאימות."
      },
      {
        "title": "קבל את הדוח שלך",
        "description": "הורד דוח PDF מפורט עם ממצאים והפניות משפטיות."
      }
    ]
  },
  "whyUs": {
    "title": "מעצימים <br />נוהלי שכר הוגנים",
    "description": "ב-Paynalyze, אנו מחויבים להגן על זכויות העובדים על ידי הבטחת קבלת תגמול הוגן וחוקי. הפלטפורמה המופעלת על ידי AI שלנו עוזרת לך לאמת בקלות תאימות שכר, לזהות הפרות ולגשת לתובנות משפטיות - הכל בשפה פשוטה.",
    "withoutTitle": "ללא Paynalyze",
    "withoutItems": [
      {
        "title": "אימות ידני",
        "description": "גוזל זמן ונוטה לטעויות."
      },
      {
        "title": "מורכבות משפטית",
        "description": "ז'רגון משפטי קשה להבנה."
      },
      {
        "title": "ידע מוגבל",
        "description": "אין גישה לתקדימים משפטיים או פסיקות רלוונטיות."
      },
      {
        "title": "אין הוכחה ברורה",
        "description": "חוסר תיעוד רשמי לתמיכה בטענות."
      }
    ],
    "withTitle": "עם Paynalyze",
    "withItems": [
      {
        "title": "ניתוח שכר מדויק",
        "description": "זהה באופן מיידי תשלומים חסרים והפרות חוק."
      },
      {
        "title": "הסברים משפטיים פשוטים",
        "description": "הבן חוקים מורכבים בשפה פשוטה."
      },
      {
        "title": "תקדימים משפטיים",
        "description": "צפה בפסיקות משפטיות רלוונטיות למקרים דומים."
      },
      {
        "title": "דוחות להורדה",
        "description": "קבל דוחות PDF מפורטים עם הפניות משפטיות."
      }
    ]
  },
  "pricing": {
    "title": "בחר את התוכנית המתאימה לך",
    "subtitle": "קבל ניתוח שכר מדויק ותובנות משפטיות עם אפשרויות תמחור גמישות.",
    "monthly": "יַרחוֹן",
    "annually": "מדי שנה",
    "discountOffer": "10% הנחה, כל הזיכויים מראש",
    "freePlan": {
      "title": "תוכנית חינם",
      "price": "$0",
      "period": "חוֹדֶשׁ",
      "description": "1 ניתוח תלוש שכר בחינם<br>אין צורך בפרטים אישיים.",
      "buttonText": "מוּפעָל",
      "features": [
        "תובנות משפטיות בסיסיות",
        "הורדת דוח PDF",
        "אין תקדימים של בית משפט",
        "אין תמיכה בעדיפות"
      ]
    },
    "basicPlan": {
      "title": "תוכנית בסיסית",
      "badge": "פּוֹפּוּלָרִי",
      "price": "$9.99",
      "period": "חוֹדֶשׁ",
      "description": "5 ניתוח תלושי שכר בחודש",
      "buttonText": "שדרג לבסיסי",
      "features": [
        "הסברים משפטיים בשפה פשוטה",
        "דוחות PDF עם הפניות משפטיות",
        "אין תקדימים של בית משפט",
        "אין תמיכה בעדיפות"
      ]
    },
    "proPlan": {
      "title": "תוכנית פרו",
      "price": "$19.99",
      "period": "חוֹדֶשׁ",
      "description": "תלוש שכר וניתוח חוזים ללא הגבלה",
      "buttonText": "שדרג לתוכנית",
      "features": [
        "הסברים משפטיים מפורטים",
        "תקדימים של בית המשפט בגין הפרות",
        "דוחות PDF להורדה",
        "תמיכת לקוחות עדיפות"
      ]
    }
  },
  "about": {
    "title": "העצמת תשלום שקיפות לכולם",
    "description": "אנו מאמינים שידע הוא כוח - ותלוש המשכורת שלך לא אמור להיות בגדר תעלומה. Paynalyze בנויה כדי לעזור לעובדים לחשוף את האמת על שכרם באמצעות בינה מלאכותית ומתקדמת בתחום דיני העבודה.",
    "stats": [
      {"value": "25,000+", "text": "נותחו תלושי שכר"},
      {"value": "1,200+", "text": "זוהו הפרות של חוקי העבודה"},
      {"value": "100%", "text": "סודי ומאובטח"},
      {"value": "24×5", "text": "תמיכה משפטית וטכנית ייעודית"}
    ],
    "whatWeDo": {
      "title": "מה אנחנו עושים ולמה אנחנו עושים את זה",
      "description": ["ב-Paynalyze, אנו עוזרים לעובדים לגלות אם הם מקבלים פיצוי הוגן - על ידי סריקת תלושי שכר וחוזי עבודה, ניתוח הנתונים ואספקת דוחות משפטיים קלים להבנה.",
        "המסע שלנו התחיל ברעיון פשוט: יותר מדי עובדים אינם מודעים לזכויותיהם. מה שהתחיל כפרויקט תשוקה גדל למשימה להביא בהירות, שקיפות והוגנות למקומות עבודה בכל מקום."]
    },
    "mission": {
      "title": "המשימה שלנו",
      "description": "לתת לכל עובד את הכלים להבין, לפקפק ולהשתלט על שכרם - כי צדק מתחיל בשקיפות.",
      "coreValues": [
        {"title": "שקיפות", "description": "אנו מאמינים שאמת בונה אמון.", "icon": "Transparency.svg"},
        {"title": "העצמה", "description": "ידע צריך להיות נגיש לכולם.", "icon": "Empowerment.svg"},
        {"title": "הגינות", "description": "כל תלוש משכורת ראוי להסתכלות נוספת.", "icon": "Fairness.svg"},
        {"title": "חדשנות", "description": "אנו רותמים בינה מלאכותית כדי לפשט תובנות משפטיות מורכבות.", "icon": "Innovation.svg"}
      ]
    }
  },
  "pricingCta": {
    "title": "בחר את התוכנית שלך פתח הגנה מלאה על השכר",
    "subtitle": "קבל דוחות מפורטים, תובנות משפטיות ואימות תאימות מלא.",
    "button": "שדרג ל-Pro"
  },
  "footer": {
    "copyright": "© <a href=\"/he\" class=\"text-dark\">paynalyze.com</a> 2025 <span class=\"text-muted px-1\">|</span> כל הזכויות שמורות.",
    "links": "<a href=\"/he/privacy\" class=\"text-dark\">מדיניות פרטיות</a> <span class=\"text-muted px-1\">|</span> <a href=\"/he/cookies\" class=\"text-dark\">מדיניות עוגיות</a>"
  },
  "submitModal": {
    "title": "הוגש בהצלחה!",
    "text": "המומחים המשפטיים ומערכת ה-AI שלנו מנתחים את הנתונים שלך.<br /> תקבל דוח מפורט בקרוב.",
    "button": "עבור לדוחות שלי",
    "statusText": "תוכל לבדוק את הסטטוס במדור הדוחות שלך."
  },
  "contact": {
    "title": "יש לך שאלות?",
    "subtitle": "צור איתנו קשר",
    "description": "מלא את הטופס למטה וספר לנו איך אנחנו יכולים לעזור.",
    "supportText": "אנחנו כאן כדי לסייע לך בכל דבר - החל מתמיכת מוצר ועד פניות לשותפות.",
    "email": "support@paynalyze.com",
    "form": {
      "title": "צור קשר",
      "subtitle": "כל שעליך לעשות הוא למלא את הטופס למטה ואנו ניצור איתך קשר בהקדם.",
      "name": "שֵׁם",
      "email": "אֶלֶקטרוֹנִי",
      "phone": "טֵלֵפוֹן",
      "message": "כיצד נוכל לעזור?",
      "submit": "שלח הודעה",
      "placeholders": {
        "name": "הזן את שמך",
        "email": "הזן את המייל שלך",
        "phone": "הזן את הטלפון שלך",
        "message": "הזן את הודעתך כאן"
      }
    }
  },
  "reports": {
    "title": "הדוחות שלי",
    "subtitle": "הצג והורד את ניתוחי השכר הקודמים שלך.",
    "filter": {
      "byDate": "לפי תאריך",
      "dateOptions": {
        "last30Days": "30 הימים האחרונים",
        "last7Days": "7 הימים האחרונים",
        "today": "הַיוֹם"
      },
      "byType": "לפי סוג",
      "typeOptions": {
        "all": "כֹּל",
        "payslip": "תלוש שכר",
        "contract": "חוֹזֶה",
        "legalScenario": "תרחיש משפטי"
      },
      "byResult": "לפי תוצאה משפטית",
      "resultOptions": {
        "all": "כֹּל",
        "compliant": "תואם",
        "nonCompliant": "לא תואם"
      }
    },
    "table": {
      "date": "תַאֲרִיך",
      "type": "סוּג",
      "status": "סטָטוּס",
      "downloadButton": "הורדה",
      "actions": "קישור להורדה",
      "viewButton": " נוֹף",
      "noReports": "אין דוחות זמינים"
    },
    "downloadAll": {
      "button": "הורד את כל הדוחות",
      "text": "קבל קובץ ZIP עם כל דוחות השכר הקודמים שלך."
    }
  },
  "signin": {
    "leftBannerTitle": "שכר חכם יותר,<br> דיוק משפטי.",
    "leftBannerImageAlt": "איור הרשמה לכניסה",
    "title": "היכנס ל- <span class=\"text-primary\">Paynalyze</span> תחילה.",
    "subtitle": "גש לתובנות השכר שלך באופן מיידי.",
    "emailPlaceholder": "הזן את המייל שלך",
    "emailLabel": "אֶלֶקטרוֹנִי",
    "passwordPlaceholder": "הזן את הסיסמה שלך",
    "passwordLabel": "סִיסמָה",
    "rememberMe": "זכור אותי",
    "forgotPassword": "שכחת סיסמא?",
    "signInButton": "היכנס",
    "orDivider": "אוֹ",
    "googleButton": "גוגל",
    "googleImageAlt": "לוגו גוגל",
    "facebookButton": "פייסבוק",
    "facebookImageAlt": "לוגו פייסבוק",
    "appleButton": "תַפּוּחַ",
    "appleImageAlt": "לוגו אפל",
    "noAccount": "אין לך חשבון Paynalyze?",
    "signUpLink": "הירשם"
  },
  "signup": {
    "leftBannerTitle": "שכר חכם יותר,<br> דיוק משפטי.",
    "rightFormTitle": "צור את חשבון <span class=\"text-primary\">Paynalyze</span> שלך.<br> התחל בחינם.",
    "rightFormSubtitle": "התחל עם ניתוח שכר חכם יותר.",
    "namePlaceholder": "הזן את שמך",
    "nameLabel": "שֵׁם",
    "emailPlaceholder": "הזן את המייל שלך",
    "emailLabel": "אֶלֶקטרוֹנִי",
    "phonePlaceholder": "הזן את הטלפון שלך",
    "phoneLabel": "טֵלֵפוֹן",
    "passwordPlaceholder": "הגדר סיסמה",
    "passwordLabel": "סִיסמָה",
    "reEnterPasswordPlaceholder": "הזן מחדש את הסיסמה",
    "reEnterPasswordLabel": "היכנס מחדש",
    "termsCheckboxLabel": "אני מסכים ל<a href=\"#\">תנאים ולהגבלות</a> ול<a href=\"#\">מדיניות הפרטיות</a>.",
    "freeSignUpButton": "הרשמה חינם",
    "orDivider": "אוֹ",
    "googleButton": "גוגל",
    "facebookButton": "פייסבוק",
    "appleButton": "תַפּוּחַ",
    "signInPrompt": "כבר יש לך חשבון Paynalyze?",
    "signInLink": "היכנס"
  },
  "subscribe": {
    "title": "הירשם ל <span class=\"text-yellow\">Paynalyze תוכנית בסיסית</span> מִנוּי",
    "price": "$9.99",
    "period": "/ חוֹדֶשׁ",
    "planDetails": {
      "title": "מנוי לתוכנית בסיסית",
      "billing": "מחויב מדי חודש",
      "price": "$9.99"
    },
    "subtotal": {
      "title": "סכום משנה",
      "taxInfo": "מַס",
      "price": "$9.99",
      "taxAmount": "$3"
    },
    "totalDue": {
      "title": "סך הכל לפירעון היום",
      "price": "$12.99"
    },
    "paymentMethodTitle": "בחר את אמצעי התשלום שלך.",
    "cardInfoLabel": "מידע על הכרטיס",
    "cardPlaceholder": "1234   1234   1234   1234",
    "expiryPlaceholder": "MM / YY",
    "cvvPlaceholder": "CVV",
    "cardholderNameLabel": "שם בעל הכרטיס",
    "cardholderNamePlaceholder": "השם המלא בכרטיס",
    "countryLabel": "מדינה",
    "countryDefault": "ישראל",
    "countryOptionUSA": "ארה\"ב",
    "countryOptionIsrael": "ישראל",
    "addressPlaceholder": "כתובת",
    "saveInfoCheckboxLabel": "שמור את המידע שלי בצורה מאובטחת עבור תשלום בלחיצה אחת",
    "saveInfoCheckboxSubtext": "שלם מהר יותר ב-Paynalyze ובכל מקום הקישור מתקבל.",
    "subscribeButton": "הירשם",
    "termsText": "על ידי אישור המנוי שלך, אתה מאפשר לנו לחייב את כרטיסכם עבור תשלומים זה ותשלומים עתידיים בהתאם לתנאים. אתה יכול תמיד לבטל את המנוי שלך"
  },
  "lawyerModal": {
    "title": "בחרו את עורך הדין המומחה שלכם לדיני עבודה",
    "lawyers": [
      {
        "name": "דוד לוי",
        "location": "תל אביב, ישראל",
        "experience": "17 שנות ניסיון בתחום דיני עבודה",
        "rating": "4.9 | מעל 120 ביקורות לקוחות",
        "specialtiesTitle": "התמחויות",
        "specialties": [
          "סכסוכי שכר",
          "פיטורים שלא כדין",
          "תביעות פיצויי פיטורים"
        ],
        "contactButton": "צור קשר עכשיו"
      },
      {
        "name": "אמיר שלו",
        "location": "ירושלים, ישראל",
        "experience": "12 שנות ניסיון בתחום דיני עבודה",
        "rating": "4.8 | מעל 100 ביקורות לקוחות",
        "specialtiesTitle": "התמחויות",
        "specialties": [
          "חוזי העסקה",
          "סכסוכי שעות נוספות שלא שולמו",
          "ייצוג בבית הדין לעבודה"
        ],
        "contactButton": "צור קשר עכשיו"
      },
      {
        "name": "מיכל ברק",
        "location": "רמת גן, ישראל",
        "experience": "11 שנות ניסיון בתחום דיני עבודה",
        "rating": "4.8 | מעל 90 ביקורות לקוחות",
        "specialtiesTitle": "התמחויות",
        "specialties": [
          "הפרות של שכר מינימום",
          "סכסוכי הטבות לעובדים",
          "תיקי פיטורים שלא כדין"
        ],
        "contactButton": "צור קשר עכשיו"
      },
      {
        "name": "איתן מויאל",
        "location": "באר שבע, ישראל",
        "experience": "20 שנות ניסיון בתחום דיני עבודה",
        "rating": "4.7 | 95+ ביקורות לקוחות",
        "specialtiesTitle": "התמחויות",
        "specialties": [
          "סכסוכי איגודים",
          "מקרי הטרדה במקום העבודה",
          "טענות נקמה"
        ],
        "contactButton": "צור קשר עכשיו"
      }
    ]
  },
  "law": {
    "title": "ניהול חוקי עבודה",
    "subtitle": "צפה, הוסף, ערוך ומחק חוקי עבודה במערכת שלנו",
    "databaseTitle": "מאגר חוקי עבודה",
    "databaseSubtitle": "נהל את כל חוקי העבודה שלך במקום אחד",
    "newLawPlaceholder": "הזן את טקסט חוק העבודה...",
    "addButton": "הוסף חוק חדש",
    "addingButton": "מוסיף...",
    "loading": "טוען...",
    "loadingLaws": "טוען חוקים...",
    "noLaws": "לא נמצאו חוקי עבודה. הוסף את החוק הראשון שלך למעלה.",
    "lawTextHeader": "טקסט החוק",
    "actionsHeader": "פעולות",
    "saveTip": "שמור שינויים",
    "saveButton": "שמור",
    "cancelTip": "בטל עריכה",
    "cancelButton": "בטל",
    "editTip": "ערוך חוק זה",
    "editButton": "ערוך",
    "deleteTip": "מחק חוק זה",
    "deleteButton": "מחק",
    "confirmDelete": "האם אתה בטוח שברצונך למחוק חוק זה?",
    "errors": {
      "fetchFailed": "שגיאה בטעינת חוקים",
      "genericFetch": "נכשל בטעינת חוקים",
      "addFailed": "שגיאה בהוספת חוק",
      "genericAdd": "נכשל בהוספת חוק",
      "deleteFailed": "שגיאה במחיקת חוק",
      "genericDelete": "נכשל במחיקת חוק",
      "updateFailed": "שגיאה בעדכון חוק",
      "genericUpdate": "נכשל בעדכון חוק"
    }
  }
}